kode_logger/__init__.py
kode_logger/formatters/__init__.py
kode_logger/formatters/json.py
kode_logger-1.0.4.dist-info/LICENSE
kode_logger-1.0.4.dist-info/METADATA
kode_logger-1.0.4.dist-info/WHEEL
kode_logger-1.0.4.dist-info/top_level.txt
kode_logger-1.0.4.dist-info/RECORD
