Metadata-Version: 2.1
Name: kode-logger
Version: 1.0.4
Summary: Encode logs to JSON format
Home-page: UNKNOWN
Author: KODE
Author-email: ashelepov@kode-t.ru
License: MIT
Platform: UNKNOWN
Classifier: Programming Language :: Python :: 3
Classifier: License :: OSI Approved :: MIT License
Classifier: Operating System :: OS Independent
Requires-Python: >=3.7
Provides-Extra: orjson
Requires-Dist: orjson (>=3.1.0) ; extra == 'orjson'
